{
	"target": "hmag:creeper_girl",
	"attributes": [
		{
			"id": "minecraft:generic.knockback_resistance",
			"modifier_name": "KnockbackResistance",
			"amount": {
				"min": 0.4,
				"max": 0.6,
				"difficulty_modifier": {
					"operation": "add",
					"easy": -0.4,
					"hard": 0.4
				}
			},
			"operation": "addition"
		},
		{
			"id": "minecraft:generic.movement_speed",
			"modifier_name": "Speed",
			"amount": {
				"value": 0.12,
				"difficulty_modifier": {
					"operation": "add",
					"normal": 0.1,
					"hard": 0.2
				}
			},
			"operation": "multiply_base"
		},
		{
			"id": "minecraft:generic.armor",
			"modifier_name": "Armor",
			"amount": {
				"value": 1,
				"difficulty_modifier": {
					"operation": "add",
					"easy": -1,
					"hard": 1
				}
			},
			"operation": "addition"
		}
	],
	"potion_effects": [
		{
			"id": "minecraft:fire_resistance",
			"hide_particles": true
		}
	],
	"creeper": {
		"fuse": {
			"value": 25,
			"difficulty_modifier": {
				"operation": "add",
				"easy": 5,
				"hard": -5
			}
		},
		"fire_chance": {
			"value": 0.3,
			"difficulty_modifier": {
				"operation": "add",
				"normal": 0.2,
				"hard": 0.7
			}
		}
	}
}